[
  {
    "Guests": 17,
    "Rooms": 9,
    "Bathrooms": 10,
    "Short_Description": "A majestic property, situated in a prime area overlooking the Aegean Sea",
    "Price": 95500,
    "Location": "37.4697107323934588,25.3374557798469056",
    "City": "Agia Sofia"
  },
  {
    "Guests": 22,
    "Rooms": 11,
    "Bathrooms": 11,
    "Short_Description": "Waterfront villa in a dream like location",
    "Price": 76370,
    "Location": "37.422806798288846,25.317115267051157",
    "City": "Ornos"
  },
  {
    "Guests": 30,
    "Rooms": 15,
    "Bathrooms": 16,
    "Short_Description": "\"Amazing estate, beach proximity, ideal for large groups & big events\"",
    "Price": 66821,
    "Location": "37.4282039832973368,25.410762199474803",
    "City": "Kalo Livadi"
  },
  {
    "Guests": 18,
    "Rooms": 8,
    "Bathrooms": 9,
    "Short_Description": "An uber-luxe exclusive private mansion with beach proximity",
    "Price": 57275,
    "Location": "37.42517678982687,25.334232375978594",
    "City": "Psarou"
  },
  {
    "Guests": 12,
    "Rooms": 6,
    "Bathrooms": 6,
    "Short_Description": "More than a villa, a true Mykonian experience!",
    "Price": 55685,
    "Location": "37.4078945945853292,25.3377755362644379",
    "City": "Agios Lazarus"
  },
  {
    "Guests": 12,
    "Rooms": 6,
    "Bathrooms": 6,
    "Short_Description": "\"Unique private residence, overlooking the port with amazing views\"",
    "Price": 52190,
    "Location": "37.4800679109844594,25.3277266993879095",
    "City": "Tourlos"
  },
  {
    "Guests": 36,
    "Rooms": 18,
    "Bathrooms": 18,
    "Short_Description": "\"A lavish property with exceptional facilities and beach proximity\"",
    "Price": 47730,
    "Location": "37.4389277492174273,25.4092831797089893",
    "City": "Kalafatis"
  },
  {
    "Guests": 16,
    "Rooms": 8,
    "Bathrooms": 14,
    "Short_Description": "Exclusive waterfront private villa with magnificent sea views and sunsets",
    "Price": 46460,
    "Location": "37.4180356853474692,25.3258258260571125",
    "City": "Agios Lazarus"
  },
  {
    "Guests": 40,
    "Rooms": 20,
    "Bathrooms": 20,
    "Short_Description": "An exclusive retreat just a short walk away from a wonderful sun-kissed sandy beach",
    "Price": 44550,
    "Location": "37.4413237106174108,25.4133031575753137",
    "City": "Kalo Livadi"
  },
  {
    "Guests": 20,
    "Rooms": 10,
    "Bathrooms": 10,
    "Short_Description": "A wonderful brand new villa with magnificent views and beach proximity",
    "Price": 44550,
    "Location": "37.4375704788917005,25.4136511467926454",
    "City": "Kalo Livadi"
  },
  {
    "Guests": 20,
    "Rooms": 10,
    "Bathrooms": 10,
    "Short_Description": "Beautiful Seafront villa with private sea access",
    "Price": 41370,
    "Location": "37.410711082894665,25.304260128803282",
    "City": "Aleomandra"
  },
  {
    "Guests": 16,
    "Rooms": 8,
    "Bathrooms": 8,
    "Short_Description": "A magnificent brand new property with amazing views and impeccable amenities",
    "Price": 41366,
    "Location": "37.4312214980628255,25.4035519472594622",
    "City": "Kalo Livadi"
  },
  {
    "Guests": 20,
    "Rooms": 10,
    "Bathrooms": 10,
    "Short_Description": "One-of-a-kind mansion few meters walking distance from the beach",
    "Price": 40095,
    "Location": "37.41501964789567,25.315021085964975",
    "City": "Aleomandra"
  },
  {
    "Guests": 10,
    "Rooms": 5,
    "Bathrooms": 6,
    "Short_Description": "A timeless Greek sanctuary with amazing sea views",
    "Price": 38185,
    "Location": "37.41823138899418,25.319113223774995",
    "City": "Aleomandra"
  },
  {
    "Guests": 20,
    "Rooms": 10,
    "Bathrooms": 11,
    "Short_Description": "\"Newly built frontline architectural jewel with panoramic sea views\"",
    "Price": 35798,
    "Location": "37.4081297488379789,25.3363590039100401",
    "City": "Agios Lazarus"
  },
  {
    "Guests": 34,
    "Rooms": 17,
    "Bathrooms": 17,
    "Short_Description": "\"A lavish complex of villas & suites with striking sea views\"",
    "Price": 31820,
    "Location": "37.4692098202323862,25.3294095714414809",
    "City": "Agia Sofia"
  },
  {
    "Guests": 20,
    "Rooms": 10,
    "Bathrooms": 11,
    "Short_Description": "A unique property where dreams come true",
    "Price": 31820,
    "Location": "37.440112651827356,25.31854724466936",
    "City": "Kanalia"
  },
  {
    "Guests": 16,
    "Rooms": 8,
    "Bathrooms": 8,
    "Short_Description": "A brand new private property with fantastic views and impeccable facilities",
    "Price": 25500,
    "Location": "37.2760567486492675,25.1949816612643112",
    "City": "Tourlos"
  },
  {
    "Guests": 16,
    "Rooms": 8,
    "Bathrooms": 8,
    "Short_Description": "\"Seafront villa in a prime location close to Paraga & Paradise beaches\"",
    "Price": 25460,
    "Location": "37.411286297253163,25.3481455992592331",
    "City": "Paranga"
  },
  {
    "Guests": 16,
    "Rooms": 8,
    "Bathrooms": 8,
    "Short_Description": "\"Wonderful seafront villa situated in a privileged area with beach proximity\"",
    "Price": 25460,
    "Location": "37.4132853986657565,25.3473088919269713",
    "City": "Paranga"
  },
  {
    "Guests": 15,
    "Rooms": 7,
    "Bathrooms": 8,
    "Short_Description": "\"Luxurious front-line estate, with splendid sea and sunset views\"",
    "Price": 25460,
    "Location": "37.4166598766160732,25.3782990343050123",
    "City": "Super Paradise"
  },
  {
    "Guests": 12,
    "Rooms": 6,
    "Bathrooms": 6,
    "Short_Description": "A brand new stylish sea view property with amazing facilities",
    "Price": 23866,
    "Location": "37.4272097874269321,25.3911371683659617",
    "City": "Elia"
  },
  {
    "Guests": 16,
    "Rooms": 8,
    "Bathrooms": 9,
    "Short_Description": "A magnificent brand new villa with direct access to the sea",
    "Price": 22280,
    "Location": "37.413101737783364,25.308874564038465",
    "City": "Aleomandra"
  },
  {
    "Guests": 16,
    "Rooms": 8,
    "Bathrooms": 9,
    "Short_Description": "Newly-built sea front property with beach proximity",
    "Price": 22280,
    "Location": "37.416301215791776,25.315897812810817",
    "City": "Aleomandra"
  },
  {
    "Guests": 18,
    "Rooms": 8,
    "Bathrooms": 9,
    "Short_Description": "Brand new frontline private home with amazing views and sunsets",
    "Price": 22280,
    "Location": "37.406527685551445,25.330668841422035",
    "City": "Agios Lazarus"
  },
  {
    "Guests": 18,
    "Rooms": 9,
    "Bathrooms": 9,
    "Short_Description": "\"A splendid sea front vacation residence with captivating views\"",
    "Price": 22275,
    "Location": "37.4236530681000872,25.3091193020800631",
    "City": "Pouli"
  },
  {
    "Guests": 18,
    "Rooms": 9,
    "Bathrooms": 9,
    "Short_Description": "\"Private seafront villa with mind-blowing sunsets & a blissful setting\"",
    "Price": 22275,
    "Location": "37.4129000776175147,25.3081810613880194",
    "City": "Aleomandra"
  },
  {
    "Guests": 16,
    "Rooms": 8,
    "Bathrooms": 8,
    "Short_Description": "\"Amazing home with elegant design and dazzling panoramic sea views \"",
    "Price": 22275,
    "Location": "37.4174287193535307,25.3114382805066462",
    "City": "Agios Ioannis"
  },
  {
    "Guests": 15,
    "Rooms": 8,
    "Bathrooms": 9,
    "Short_Description": "\"A fantastic luxurious home located on a unique spot of Mykonos\"",
    "Price": 22275,
    "Location": "37.4197900114964668,25.3331836877086971",
    "City": "Agios Lazarus"
  },
  {
    "Guests": 18,
    "Rooms": 9,
    "Bathrooms": 9,
    "Short_Description": "A unique brand new property with fantastic views and facilities",
    "Price": 21640,
    "Location": "37.4758344708028304,25.3111428307747026",
    "City": "Choulakia"
  },
  {
    "Guests": 11,
    "Rooms": 5,
    "Bathrooms": 7,
    "Short_Description": "\"This spectacular luxury villa is the epitome of privacy and seclusion\"",
    "Price": 21001,
    "Location": "37.4093804228405276,25.3730147623904649",
    "City": "Super Paradise"
  },
  {
    "Guests": 13,
    "Rooms": 6,
    "Bathrooms": 6,
    "Short_Description": "\"A stylish newly built villa with walking distance from Psarou beach\"",
    "Price": 20370,
    "Location": "37.4136448519951799,25.3297996463692883",
    "City": "Agios Lazarus"
  },
  {
    "Guests": 12,
    "Rooms": 6,
    "Bathrooms": 6,
    "Short_Description": "A newly built luxurious house close to the town of Mykonos",
    "Price": 20370,
    "Location": "37.4363985842152616,25.3313644394557542",
    "City": "Mykonos Town"
  },
  {
    "Guests": 12,
    "Rooms": 6,
    "Bathrooms": 6,
    "Short_Description": "A stunning private mansion with beach proximity",
    "Price": 20370,
    "Location": "37.45030854536707,25.37656801069652",
    "City": "Ftelia"
  },
  {
    "Guests": 15,
    "Rooms": 8,
    "Bathrooms": 8,
    "Short_Description": "Beautiful private house with alluring sea & sunset views",
    "Price": 20370,
    "Location": "37.41540987063136,25.307767148712465",
    "City": "Aleomandra"
  },
  {
    "Guests": 24,
    "Rooms": 10,
    "Bathrooms": 10,
    "Short_Description": "A majestic Mykonian estate with premium accommodation and amazing views",
    "Price": 19100,
    "Location": "37.4286598469350125,25.3730666395878188",
    "City": "Agrari"
  },
  {
    "Guests": 12,
    "Rooms": 6,
    "Bathrooms": 7,
    "Short_Description": "\"A unique waterfront home that will impress each guest in every way\"",
    "Price": 19095,
    "Location": "37.4167260521880038,25.3253865701664473",
    "City": "Agios Lazarus"
  },
  {
    "Guests": 12,
    "Rooms": 6,
    "Bathrooms": 6,
    "Short_Description": "Private luxurious villa with mind-blowing sunsets & a blissful setting",
    "Price": 19095,
    "Location": "37.40754942662374,25.328382342817115",
    "City": "Agios Lazarus"
  },
  {
    "Guests": 18,
    "Rooms": 9,
    "Bathrooms": 11,
    "Short_Description": "\"An elegant luxurious home with fabulous sea and sunset views\"",
    "Price": 18183,
    "Location": "37.408919072455376,25.3384858717978254",
    "City": "Agios Lazarus"
  },
  {
    "Guests": 18,
    "Rooms": 9,
    "Bathrooms": 10,
    "Short_Description": "This Spectacular villa will welcome guests in stylish luxury",
    "Price": 15911,
    "Location": "37.427814418451085,25.331525354562896",
    "City": "Ornos"
  },
  {
    "Guests": 14,
    "Rooms": 7,
    "Bathrooms": 7,
    "Short_Description": "\"An incredible front line villa with majestic sea and sunset views\"",
    "Price": 15910,
    "Location": "37.4318993793747339,25.2997519428695554",
    "City": "Pouli"
  },
  {
    "Guests": 12,
    "Rooms": 6,
    "Bathrooms": 6,
    "Short_Description": "A wonderful seafront property located in one of the most in demand areas",
    "Price": 15910,
    "Location": "37.4073861292801979,25.3275055877165407",
    "City": "Agios Lazarus"
  },
  {
    "Guests": 10,
    "Rooms": 5,
    "Bathrooms": 5,
    "Short_Description": "Unique private property offering outstanding sea views",
    "Price": 15910,
    "Location": "37.4665597592901563,25.3194658013373513",
    "City": "Tourlos"
  },
  {
    "Guests": 8,
    "Rooms": 4,
    "Bathrooms": 4,
    "Short_Description": "Exclusive villa, prime location, panoramic views & magical sunsets",
    "Price": 15910,
    "Location": "37.41840704508178,25.325165029392025",
    "City": "Agios Lazarus"
  },
  {
    "Guests": 12,
    "Rooms": 6,
    "Bathrooms": 7,
    "Short_Description": "A newly-built waterfront property in Aleomandra with amazing unobstructed sea views",
    "Price": 15300,
    "Location": "37.4038311225303062,25.309552968707834",
    "City": "Aleomandra"
  },
  {
    "Guests": 14,
    "Rooms": 7,
    "Bathrooms": 7,
    "Short_Description": "A lovely beachfront property right on the golden sandy beach of Ftelia",
    "Price": 15300,
    "Location": "37.4580313172633055,25.3678196004386294",
    "City": "Ftelia"
  },
  {
    "Guests": 12,
    "Rooms": 6,
    "Bathrooms": 6,
    "Short_Description": "A luxurious private villa with amazingly beautiful sunsets",
    "Price": 15300,
    "Location": "37.4266430749673233,25.3086445627876806",
    "City": "Agios Ioannis"
  },
  {
    "Guests": 16,
    "Rooms": 8,
    "Bathrooms": 8,
    "Short_Description": "\"A splendid Villa located in a prime area overlooking the Aegean Sea\"",
    "Price": 15275,
    "Location": "37.4696284877576034,25.3402070181659873",
    "City": "Agia Sofia"
  },
  {
    "Guests": 14,
    "Rooms": 7,
    "Bathrooms": 7,
    "Short_Description": "\"A fantastic home close to town with beautiful sea and sunset views\"",
    "Price": 14640,
    "Location": "37.4749365548807205,25.3098235284608037",
    "City": "Agios Stefanos"
  },
  {
    "Guests": 10,
    "Rooms": 5,
    "Bathrooms": 5,
    "Short_Description": "An amazing villa designed to make the most of the idyllic island lifestyle",
    "Price": 14640,
    "Location": "37.4051237642548386,25.3061342069638258",
    "City": "Aleomandra"
  },
  {
    "Guests": 11,
    "Rooms": 5,
    "Bathrooms": 5,
    "Short_Description": "\"A glamorous newly built villa with uninterrupted sea views\"",
    "Price": 14002,
    "Location": "37.4094591080184813,25.3345198662416635",
    "City": "Agios Lazarus"
  },
  {
    "Guests": 18,
    "Rooms": 8,
    "Bathrooms": 8,
    "Short_Description": "\"A splendid family owned villa with panoramic sea and sunset views\"",
    "Price": 14002,
    "Location": "37.4290026585394529,25.3533916059603435",
    "City": "Kounoupas"
  }
]